setup.py
django_realtime.egg-info/PKG-INFO
django_realtime.egg-info/SOURCES.txt
django_realtime.egg-info/dependency_links.txt
django_realtime.egg-info/top_level.txt
drealtime/__init__.py
drealtime/middleware.py
drealtime/templatetags/__init__.py
drealtime/templatetags/drealtimetags.py