Metadata-Version: 1.1
Name: django-realtime
Version: 1.1
Summary: an iShout.js client for Django
Home-page: https://bitbucket.org/inzane/django-realtime
Author: Anish menon
Author-email: anish@inzane.in
License: MIT
Platform: UNKNOWN
Classifier: Development Status :: 3 - Alpha
Classifier: Environment :: Web Environment
Classifier: Intended Audience :: Developers
Classifier: License :: OSI Approved :: MIT License
Classifier: Operating System :: OS Independent
Classifier: Programming Language :: Python
Classifier: Framework :: Django
